aw_client/__init__.py
aw_client/__main__.py
aw_client/classes.py
aw_client/cli.py
aw_client/client.py
aw_client/config.py
aw_client/py.typed
aw_client/queries.py
aw_client/singleinstance.py
aw_client-0.5.15.dist-info/LICENSE.txt
aw_client-0.5.15.dist-info/METADATA
aw_client-0.5.15.dist-info/WHEEL
aw_client-0.5.15.dist-info/entry_points.txt
aw_client-0.5.15.dist-info/RECORD
