Metadata-Version: 2.1
Name: aw-client
Version: 0.5.15
Summary: Client library for ActivityWatch
Home-page: https://activitywatch.net/
License: MPL-2.0
Author: Erik Bjäreholt
Author-email: erik@bjareho.lt
Requires-Python: >=3.8,<4.0
Classifier: License :: OSI Approved
Classifier: Programming Language :: Python :: 3
Classifier: Programming Language :: Python :: 3.8
Classifier: Programming Language :: Python :: 3.9
Classifier: Programming Language :: Python :: 3.10
Classifier: Programming Language :: Python :: 3.11
Requires-Dist: aw-core (>=0.5.16,<0.6.0)
Requires-Dist: click (>=8.0,<9.0)
Requires-Dist: persist-queue
Requires-Dist: requests
Requires-Dist: tabulate
Requires-Dist: typing-extensions
Project-URL: Documentation, https://docs.activitywatch.net/
Project-URL: Repository, https://github.com/ActivityWatch/aw-client/
